wolvesburg/__init__.py
Wolvesburg-3.3.0.dist-info/LICENSE.txt
Wolvesburg-3.3.0.dist-info/METADATA
Wolvesburg-3.3.0.dist-info/WHEEL
Wolvesburg-3.3.0.dist-info/top_level.txt
Wolvesburg-3.3.0.dist-info/RECORD
